siglab_py/__init__.py
siglab_py/constants.py
siglab_py/algo/__init__.py
siglab_py/algo/macdrsi_crosses_15m_tc_strategy.py
siglab_py/algo/strategy_base.py
siglab_py/algo/strategy_executor.py
siglab_py/algo/tp_algo.py
siglab_py/backtests/__init__.py
siglab_py/backtests/backtest_core.py
siglab_py/backtests/coinflip_15m_crypto.py
siglab_py/backtests/fibonacci_d_mv_crypto.py
siglab_py/backtests/macdrsi_crosses_15m_tc_crypto.py
siglab_py/exchanges/__init__.py
siglab_py/exchanges/any_exchange.py
siglab_py/exchanges/binance.py
siglab_py/exchanges/deribit.py
siglab_py/exchanges/futubull.py
siglab_py/exchanges/okx.py
siglab_py/market_data_providers/__init__.py
siglab_py/market_data_providers/aggregated_orderbook_provider.py
siglab_py/market_data_providers/candles_provider.py
siglab_py/market_data_providers/candles_ta_provider.py
siglab_py/market_data_providers/ccxt_candles_ta_to_csv.py
siglab_py/market_data_providers/deribit_options_expiry_provider.py
siglab_py/market_data_providers/futu_candles_ta_to_csv.py
siglab_py/market_data_providers/google_monitor.py
siglab_py/market_data_providers/orderbooks_provider.py
siglab_py/market_data_providers/tg_monitor.py
siglab_py/market_data_providers/trigger_provider.py
siglab_py/ordergateway/__init__.py
siglab_py/ordergateway/client.py
siglab_py/ordergateway/encrypt_keys_util.py
siglab_py/ordergateway/gateway.py
siglab_py/ordergateway/test_ordergateway.py
siglab_py/tests/__init__.py
siglab_py/tests/integration/__init__.py
siglab_py/tests/integration/market_data_util_tests.py
siglab_py/tests/unit/__init__.py
siglab_py/tests/unit/analytic_util_tests.py
siglab_py/tests/unit/market_data_util_tests.py
siglab_py/tests/unit/simple_math_tests.py
siglab_py/tests/unit/trading_util_tests.py
siglab_py/util/__init__.py
siglab_py/util/analytic_util.py
siglab_py/util/aws_util.py
siglab_py/util/datetime_util.py
siglab_py/util/market_data_util.py
siglab_py/util/module_util.py
siglab_py/util/notification_util.py
siglab_py/util/retry_util.py
siglab_py-0.7.10.dist-info/METADATA
siglab_py-0.7.10.dist-info/WHEEL
siglab_py-0.7.10.dist-info/top_level.txt
siglab_py-0.7.10.dist-info/RECORD
