Metadata-Version: 2.4
Name: siglab_py
Version: 0.7.10
Summary: Market data fetches, TA calculations and generic order gateway.
Author: r0bbarh00d
Author-email: r0bbarh00d <r0bbarh00d@gmail.com>
License: MIT
Project-URL: Homepage, https://github.com/r0bbar/siglab/blob/master/siglab_py/README.md
Requires-Python: >=3.9.19
Requires-Dist: python-dotenv
Requires-Dist: dotmap
Requires-Dist: typing_extensions
Requires-Dist: arrow
Requires-Dist: tzlocal
Requires-Dist: nest_asyncio
Requires-Dist: pandas
Requires-Dist: numpy
Requires-Dist: boto3
Requires-Dist: web3
Requires-Dist: ccxt
Requires-Dist: ccxtpro
Requires-Dist: yfinance
Requires-Dist: yahoofinancials
Requires-Dist: hurst
Requires-Dist: redis
Requires-Dist: redis-py-cluster
Requires-Dist: kafka-python
